{
    "Ar36": {
        "error": 0.0017303009809917366, 
        "fit": "Parabolic", 
        "value": 0.027816417736192693
    }, 
    "Ar37": {
        "error": 0.046552988361273653, 
        "fit": "linear", 
        "value": 0.0018682558056164465
    }, 
    "Ar38": {
        "error": 0.020907391765704768, 
        "fit": "linear", 
        "value": 1.1049093297761703
    }, 
    "Ar39": {
        "error": 0.092206502249182212, 
        "fit": "Parabolic", 
        "value": 93.540012396358833
    }, 
    "Ar40": {
        "error": 0.33198236866463116, 
        "fit": "Parabolic", 
        "value": 1296.529106600108
    }, 
    "Ar41": {
        "error": 0.10673237499088099, 
        "fit": "linear", 
        "value": -0.15326257470489058
    }
}