{
    "AX": {
        "error": 0.05385230441462954, 
        "fit": "average", 
        "value": -0.1490490561800784
    }, 
    "CDD": {
        "error": 2.353635319490453e-05, 
        "fit": "average", 
        "value": 3.7530964618781583e-06
    }, 
    "H1": {
        "error": 0.03170831035225271, 
        "fit": "average", 
        "value": -0.034018472625965454
    }, 
    "H2": {
        "error": 0.09836247375905223, 
        "fit": "average", 
        "value": -0.22037238124254588
    }, 
    "L1": {
        "error": 0.015170342882954654, 
        "fit": "average", 
        "value": -0.03057918561709039
    }, 
    "L2": {
        "error": 0.049529527017548036, 
        "fit": "average", 
        "value": -0.007920233398369324
    }
}