{
    "AX": {
        "error": 0.04265965130832057, 
        "fit": "average", 
        "value": -0.19838456288639422
    }, 
    "CDD": {
        "error": 2.706104756606665e-05, 
        "fit": "average", 
        "value": 5.004128615837544e-06
    }, 
    "H1": {
        "error": 0.03819278642440894, 
        "fit": "average", 
        "value": -0.0454000215732494
    }, 
    "H2": {
        "error": 0.10403365128568787, 
        "fit": "average", 
        "value": -0.19682577656172012
    }, 
    "L1": {
        "error": 0.01940181700174222, 
        "fit": "average", 
        "value": -0.020332534353783877
    }, 
    "L2": {
        "error": 0.0521805002814996, 
        "fit": "average", 
        "value": -0.022744723327973747
    }
}