{
    "Ar36": {
        "error": 0.0014885530184817022, 
        "fit": "Linear", 
        "value": 0.012858666845323262
    }, 
    "Ar37": {
        "error": 0.049113222532818926, 
        "fit": "linear", 
        "value": 0.062122126883720513
    }, 
    "Ar38": {
        "error": 0.018350347932904881, 
        "fit": "linear", 
        "value": 0.14495906433745628
    }, 
    "Ar39": {
        "error": 0.064315128900598179, 
        "fit": "Linear", 
        "value": 13.635605480202308
    }, 
    "Ar40": {
        "error": 0.25938975442061163, 
        "fit": "Linear", 
        "value": 858.38337132400818
    }, 
    "Ar41": {
        "error": 0.10299847575121127, 
        "fit": "Average", 
        "value": -0.17594074569579615
    }
}