{
    "Ar36": {
        "error": 0.0005607511387200408, 
        "filter_outliers": true, 
        "fit": "Parabolic", 
        "iterations": 1, 
        "std_devs": 2, 
        "value": 0.013627909271229425
    }, 
    "Ar37": {
        "error": 0.009737920119627267, 
        "filter_outliers": true, 
        "fit": "Linear", 
        "iterations": 1, 
        "std_devs": 2, 
        "value": 0.06338701797578113
    }, 
    "Ar38": {
        "error": 0.004236064103438991, 
        "filter_outliers": true, 
        "fit": "Linear", 
        "iterations": 1, 
        "std_devs": 2, 
        "value": 0.10555063561588066
    }, 
    "Ar39": {
        "error": 0.02148758957403933, 
        "filter_outliers": true, 
        "fit": "Parabolic", 
        "iterations": 1, 
        "std_devs": 2, 
        "value": 11.009812280525217
    }, 
    "Ar40": {
        "error": 0.07136520055871454, 
        "filter_outliers": true, 
        "fit": "Parabolic", 
        "iterations": 1, 
        "std_devs": 2, 
        "value": 690.4374585718509
    }, 
    "Ar41": {
        "error": 0.008828717554950287, 
        "filter_outliers": true, 
        "fit": "Average", 
        "iterations": 1, 
        "std_devs": 2, 
        "value": -0.15972338130955305
    }, 
    "reviewed": true
}