{
    "Ar36": {
        "error": 0.0003402630315859827, 
        "filter_outliers": true, 
        "fit": "Parabolic", 
        "iterations": 1, 
        "std_devs": 2, 
        "value": 0.0038151442488843783
    }, 
    "Ar37": {
        "error": 0.011269231896651109, 
        "filter_outliers": true, 
        "fit": "Linear", 
        "iterations": 1, 
        "std_devs": 2, 
        "value": 0.057296997418980734
    }, 
    "Ar38": {
        "error": 0.004616093682971745, 
        "filter_outliers": true, 
        "fit": "Linear", 
        "iterations": 1, 
        "std_devs": 2, 
        "value": 0.14325050120694804
    }, 
    "Ar39": {
        "error": 0.024577763157663985, 
        "filter_outliers": true, 
        "fit": "Parabolic", 
        "iterations": 1, 
        "std_devs": 2, 
        "value": 14.152013741553015
    }, 
    "Ar40": {
        "error": 0.08851584425975956, 
        "filter_outliers": true, 
        "fit": "Parabolic", 
        "iterations": 1, 
        "std_devs": 2, 
        "value": 889.7339946089126
    }, 
    "Ar41": {
        "error": 0.008411173989317235, 
        "filter_outliers": true, 
        "fit": "Average", 
        "iterations": 1, 
        "std_devs": 2, 
        "value": 0.06667873793218321
    }, 
    "reviewed": true
}