{
    "Ar36": {
        "error": 0.0015233255647123967, 
        "fit": "Linear", 
        "value": 0.020719689087352645
    }, 
    "Ar37": {
        "error": 0.04979284235982654, 
        "fit": "linear", 
        "value": 0.092741760016186336
    }, 
    "Ar38": {
        "error": 0.020666813075525776, 
        "fit": "linear", 
        "value": 0.2444191678085674
    }, 
    "Ar39": {
        "error": 0.054967325886604974, 
        "fit": "Linear", 
        "value": 21.439505086248236
    }, 
    "Ar40": {
        "error": 0.31893482436285903, 
        "fit": "Linear", 
        "value": 1350.6480543537032
    }, 
    "Ar41": {
        "error": 0.12047044183408398, 
        "fit": "Average", 
        "value": -0.14456151587200231
    }
}