{
    "Ar36": {
        "error": 0.0015443166178103068, 
        "fit": "Linear", 
        "value": 0.01612153120924574
    }, 
    "Ar37": {
        "error": 0.049226944710358767, 
        "fit": "linear", 
        "value": 0.11002732804696898
    }, 
    "Ar38": {
        "error": 0.023983457005378853, 
        "fit": "linear", 
        "value": 0.22202860315649595
    }, 
    "Ar39": {
        "error": 0.056047285497976891, 
        "fit": "Linear", 
        "value": 20.802702631963143
    }, 
    "Ar40": {
        "error": 0.33019567288038931, 
        "fit": "Linear", 
        "value": 1318.7803212398399
    }, 
    "Ar41": {
        "error": 0.084606409303548347, 
        "fit": "Average", 
        "value": -0.18246384822136819
    }
}