{
    "Ar36": {
        "error": 0.0053285944415106959, 
        "fit": "Parabolic", 
        "value": 0.2274546339106675
    }, 
    "Ar37": {
        "error": 0.04874548077587583, 
        "fit": "linear", 
        "value": 0.012690346281368736
    }, 
    "Ar38": {
        "error": 0.020701234078630504, 
        "fit": "linear", 
        "value": 0.021780005685139919
    }, 
    "Ar39": {
        "error": 0.05065497389060554, 
        "fit": "Parabolic", 
        "value": -0.12957029741043122
    }, 
    "Ar40": {
        "error": 0.073107079040960379, 
        "fit": "Parabolic", 
        "value": 68.928661692525679
    }, 
    "Ar41": {
        "error": 0.1129216164450223, 
        "fit": "linear", 
        "value": -0.19043317034701238
    }
}