{
    "AX": {
        "error": 0.045720408125285404, 
        "fit": "average", 
        "value": -0.1501506643467828
    }, 
    "CDD": {
        "error": 0.00015010264938359973, 
        "fit": "average", 
        "value": 0.00022768784959528905
    }, 
    "H1": {
        "error": 0.04842338060585635, 
        "fit": "average", 
        "value": 0.020525539665597312
    }, 
    "H2": {
        "error": 0.08426464557007189, 
        "fit": "average", 
        "value": -0.17011743274934846
    }, 
    "L1": {
        "error": 0.019386183059718374, 
        "fit": "average", 
        "value": -0.02901112139911025
    }, 
    "L2": {
        "error": 0.045313107783951576, 
        "fit": "average", 
        "value": -0.01589780415464514
    }
}