{
    "AX": {
        "error": 0.056509494653294044, 
        "fit": "average", 
        "value": -0.15148698840418767
    }, 
    "CDD": {
        "error": 0.00012163712495892915, 
        "fit": "average", 
        "value": 0.0001150949579217316
    }, 
    "H1": {
        "error": 0.041492928843640135, 
        "fit": "average", 
        "value": -0.0038845375903682517
    }, 
    "H2": {
        "error": 0.09475573471981995, 
        "fit": "average", 
        "value": -0.2462633201918964
    }, 
    "L1": {
        "error": 0.017639459803355614, 
        "fit": "average", 
        "value": -0.03607061751219526
    }, 
    "L2": {
        "error": 0.03985903165334506, 
        "fit": "average", 
        "value": -0.008794360986312626
    }
}