{
    "AX": {
        "error": 0.052377418966048174, 
        "fit": "average", 
        "value": -0.13820067819273263
    }, 
    "CDD": {
        "error": 0.0001732562570108212, 
        "fit": "average", 
        "value": 0.00021267546423284027
    }, 
    "H1": {
        "error": 0.03324867691935163, 
        "fit": "average", 
        "value": -0.0009277415869417319
    }, 
    "H2": {
        "error": 0.07750205988575547, 
        "fit": "average", 
        "value": -0.1911048867919466
    }, 
    "L1": {
        "error": 0.02178853919368022, 
        "fit": "average", 
        "value": -0.03145726618421232
    }, 
    "L2": {
        "error": 0.05257207612598304, 
        "fit": "average", 
        "value": -0.009653848763391898
    }
}