{
    "AX": {
        "error": 0.04721985510447089, 
        "fit": "average", 
        "value": -0.15100552893147387
    }, 
    "CDD": {
        "error": 0.00012077043394707176, 
        "fit": "average", 
        "value": 0.00011759702198711844
    }, 
    "H1": {
        "error": 0.03558741189850299, 
        "fit": "average", 
        "value": -0.011612426336796489
    }, 
    "H2": {
        "error": 0.08934907313333627, 
        "fit": "average", 
        "value": 0.06312904587989165
    }, 
    "L1": {
        "error": 0.011969699340242146, 
        "fit": "average", 
        "value": -0.030943125187020217
    }, 
    "L2": {
        "error": 0.03977843031333851, 
        "fit": "average", 
        "value": -0.006026310143559905
    }
}